nlpbasekit-0.1.4.dist-info/licenses/LICENSE
nlpkit/__init__.py
nlpkit/app.py
nlpbasekit-0.1.4.dist-info/METADATA
nlpbasekit-0.1.4.dist-info/WHEEL
nlpbasekit-0.1.4.dist-info/top_level.txt
nlpbasekit-0.1.4.dist-info/RECORD
