Metadata-Version: 2.4
Name: nlpbasekit
Version: 0.1.4
Summary: An easy-to-use library with advanced preprocessing features to streamline and accelerate machine learning workflows.
Author-email: Muhammad Talha Sharif <745talha@gmail.com>, Anees Ur Rehman <aneesafridi50@gmail.com>
Maintainer-email: Anees Ur Rehman <aneesafridi50@gmail.com>
License: =The MIT License (MIT)
Keywords: nlp,text-classification,machine-learning,scikit-learn
Classifier: Intended Audience :: Science/Research
Classifier: Operating System :: OS Independent
Classifier: License :: OSI Approved :: MIT License
Classifier: Programming Language :: Python :: 3 :: Only
Classifier: Programming Language :: Python :: 3.9
Classifier: Programming Language :: Python :: 3.10
Classifier: Programming Language :: Python :: 3.11
Classifier: Programming Language :: Python :: 3.12
Classifier: Topic :: Scientific/Engineering :: Artificial Intelligence
Requires-Python: <3.13,>=3.9
License-File: LICENSE
Requires-Dist: scikit-learn>=1.2
Requires-Dist: pandas>=1.5
Requires-Dist: numpy>=1.23
Requires-Dist: nltk>=3.8
Requires-Dist: gensim>=4.3
Requires-Dist: contractions>=0.1
Requires-Dist: joblib>=1.3
Provides-Extra: dev
Requires-Dist: pytest; extra == "dev"
Requires-Dist: ruff; extra == "dev"
Requires-Dist: black; extra == "dev"
Requires-Dist: build; extra == "dev"
Requires-Dist: twine; extra == "dev"
Dynamic: license-file
